CHANGES
COPYING.LGPLv3
LICENSE
MANIFEST.in
README
ez_setup.py
requirements.txt
setup.py
django_migrator.egg-info/PKG-INFO
django_migrator.egg-info/SOURCES.txt
django_migrator.egg-info/dependency_links.txt
django_migrator.egg-info/requires.txt
django_migrator.egg-info/top_level.txt
migrator/__init__.py
migrator/admin.py
migrator/exceptions.py
migrator/models.py
migrator/tests.py
migrator/views.py
migrator/management/__init__.py
migrator/management/base.py
migrator/management/commands/__init__.py
migrator/management/commands/delete_migrated_objects.py
migrator/migrations/0001_initial.py
migrator/migrations/0002_add_migration_fields_used_field.py
migrator/migrations/0003_add_object_name_field.py
migrator/migrations/0004_add_errors_fields.py
migrator/migrations/0005_add_migration_key_field.py
migrator/migrations/0006_add_is_created_field.py
migrator/migrations/0007_add_object_url_field.py
migrator/migrations/__init__.py